{
  "ingredient": {
    "type": "item",
    "code": "game:clay-*",
    "name": "color",
    "allowedVariants": ["blue", "fire", "red"]
  },
  "pattern": [
    [
      "##############",
      "##############",
      "##############",
      "##############",
      "##############",
      "##############",
      "##############",
      "##############",
      "##############",
      "##############",
      "##############",
      "##############",
      "##############",
      "##############"
    ],
    [
      "##############",
      "##############",
      "##__________##",
      "##__________##",
      "##__________##",
      "##__________##",
      "##__________##",
      "##__________##",
      "##__________##",
      "##__________##",
      "##__________##",
      "##__________##",
      "##############",
      "##############"
    ]
  ],
  "name": "Plate Mold",
  "output": { "type": "block", "code": "smex:toolmold-{color}-raw-plate" }
}
